lyricsmaster/__init__.py
lyricsmaster/cli.py
lyricsmaster/models.py
lyricsmaster/providers.py
lyricsmaster/utils.py
lyricsmaster-2.8.1.dist-info/AUTHORS.rst
lyricsmaster-2.8.1.dist-info/LICENSE
lyricsmaster-2.8.1.dist-info/METADATA
lyricsmaster-2.8.1.dist-info/WHEEL
lyricsmaster-2.8.1.dist-info/entry_points.txt
lyricsmaster-2.8.1.dist-info/top_level.txt
lyricsmaster-2.8.1.dist-info/RECORD
