Metadata-Version: 2.1
Name: lyricsmaster
Version: 2.8.1
Summary: LyricsMaster is a library for downloading lyrics from multiple lyrics providers. LyricWiki, AzLyrics, Genius, Lyrics007, MusixMatch and other lyrics provider are available
Home-page: https://github.com/SekouD/lyricsmaster
Author: SekouD
Author-email: sekoud.python@gmail.com
License: MIT license
Keywords: lyricsmaster lyrics LyricWiki Lyrics Wikia Lyrics007 AzLyrics Genius MusixMatch Tor
Platform: UNKNOWN
Classifier: Development Status :: 5 - Production/Stable
Classifier: Topic :: Communications
Classifier: Topic :: Internet :: WWW/HTTP :: Indexing/Search
Classifier: Topic :: Software Development :: Libraries :: Python Modules
Classifier: Intended Audience :: Developers
Classifier: Intended Audience :: End Users/Desktop
Classifier: License :: OSI Approved :: MIT License
Classifier: Natural Language :: English
Classifier: Programming Language :: Python :: 2
Classifier: Programming Language :: Python :: 2.7
Classifier: Programming Language :: Python :: 3
Classifier: Programming Language :: Python :: 3.3
Classifier: Programming Language :: Python :: 3.4
Classifier: Programming Language :: Python :: 3.5
Classifier: Programming Language :: Python :: 3.6
Requires-Dist: Click (>=6.0)
Requires-Dist: lxml
Requires-Dist: beautifulsoup4
Requires-Dist: urllib3
Requires-Dist: urllib3[secure]
Requires-Dist: pysocks
Requires-Dist: gevent
Requires-Dist: stem
Requires-Dist: certifi
